rethink/__init__.py
rethink/answer_corrector.py
rethink/utils.py
rethink-0.0.2.dist-info/LICENSE
rethink-0.0.2.dist-info/METADATA
rethink-0.0.2.dist-info/WHEEL
rethink-0.0.2.dist-info/top_level.txt
rethink-0.0.2.dist-info/RECORD
