Metadata-Version: 2.1
Name: rethink
Version: 0.0.2
License-File: LICENSE
Requires-Dist: torch
Requires-Dist: transformers
Requires-Dist: tqdm
